tinkermodellor/__init__.py
tinkermodellor/model_build/__init__.py
tinkermodellor/model_build/_tkm.py
tinkermodellor/model_build/_class/__init__.py
tinkermodellor/model_build/_class/_gmxmolecule.py
tinkermodellor/model_build/_class/_tkm_atom.py
tinkermodellor/model_build/_class/_tkm_system.py
tinkermodellor/model_build/para_trans/__init__.py
tinkermodellor/model_build/para_trans/_abc.py
tinkermodellor/model_build/para_trans/amoebabio18/__init__.py
tinkermodellor/model_build/para_trans/amoebabio18/_amber.py
tinkermodellor/model_build/para_trans/amoebabio18/_forcefieldtrans.py
tinkermodellor/model_build/para_trans/amoebabio18/_gaff.py
tinkermodellor/model_build/para_trans/amoebabio18/_water_ions_trans.py
tinkermodellor-0.1.dist-info/LICENSE
tinkermodellor-0.1.dist-info/METADATA
tinkermodellor-0.1.dist-info/WHEEL
tinkermodellor-0.1.dist-info/top_level.txt
tinkermodellor-0.1.dist-info/RECORD
