Metadata-Version: 2.1
Name: tinkermodellor
Version: 0.1
Summary: TinkerModellor
Home-page: https://github.com/Hsuchein/TinkerModellor
Author: Xujian Wang, Haodong Liu
Requires-Python: >=3.6
License-File: LICENSE
